TyroBot/__init__.py
TyroBot/rubika.py
TyroBot-2.0.6.dist-info/LICENSE
TyroBot-2.0.6.dist-info/METADATA
TyroBot-2.0.6.dist-info/WHEEL
TyroBot-2.0.6.dist-info/top_level.txt
TyroBot-2.0.6.dist-info/RECORD
