Metadata-Version: 2.1
Name: TyroBot
Version: 2.0.6
Summary: This is a powerful library for building self robots in Rubika
Home-page: https://github.com/mrsalari/TyroBot
Author: mohammad saeed salari
Author-email: salari601601@gmail.com
Keywords: rubika,rubino,tyrobot,pyrubika,rubika bot,rubika library,rubx,rubika-bot,rubika-lib,bot,self bot,rubika.ir,asyncio
Classifier: Programming Language :: Python :: 3.6
Classifier: Programming Language :: Python :: 3.7
Classifier: Programming Language :: Python :: 3.8
Classifier: Programming Language :: Python :: 3.9
Classifier: Programming Language :: Python :: 3.10
Classifier: Programming Language :: Python :: 3.11
Classifier: License :: OSI Approved :: MIT License
Requires-Python: ~=3.7
License-File: LICENSE
Requires-Dist: pycryptodome
Requires-Dist: websocket-client
Requires-Dist: websockets
Requires-Dist: requests
Requires-Dist: aiohttp
Requires-Dist: pillow
Requires-Dist: mutagen
Requires-Dist: tinytag
